platform_client/__init__.py
platform_client/authentication.py
platform_client/configuration.py
platform_client/entity_engine.py
platform_client-0.31.0.dist-info/LICENSE
platform_client-0.31.0.dist-info/METADATA
platform_client-0.31.0.dist-info/WHEEL
platform_client-0.31.0.dist-info/top_level.txt
platform_client-0.31.0.dist-info/RECORD
