Metadata-Version: 2.1
Name: platform-client
Version: 0.31.0
Summary: An Evidentiq Platform client library
Home-page: https://github.com/pypa/sampleproject
Author: Evidentiq
Author-email: info@evidentiq.com
License: UNKNOWN
Platform: UNKNOWN
Classifier: Development Status :: 3 - Alpha
Classifier: Intended Audience :: Developers
Classifier: Topic :: Software Development :: Libraries
Classifier: License :: OSI Approved :: MIT License
Requires-Python: >=3.6
License-File: LICENSE
Requires-Dist: requests[security] (~=2.28)
Requires-Dist: boto3 (~=1.24)
Requires-Dist: enforce-typing (~=1.0)
Requires-Dist: sentinels (~=1.0)
Requires-Dist: frozendict (~=2.3)
Requires-Dist: http-constants (~=0.5)
Requires-Dist: hyperlink (~=21.0)
Provides-Extra: dev
